README.md
setup.py
open_nre.egg-info/PKG-INFO
open_nre.egg-info/SOURCES.txt
open_nre.egg-info/dependency_links.txt
open_nre.egg-info/requires.txt
open_nre.egg-info/top_level.txt
opennre/__init__.py
opennre/pretrain.py
opennre/encoder/__init__.py
opennre/encoder/base_encoder.py
opennre/encoder/bert_encoder.py
opennre/encoder/cnn_encoder.py
opennre/encoder/pcnn_encoder.py
opennre/framework/__init__.py
opennre/framework/bag_re.py
opennre/framework/data_loader.py
opennre/framework/multi_label_sentence_re.py
opennre/framework/sentence_re.py
opennre/framework/utils.py
opennre/model/__init__.py
opennre/model/bag_attention.py
opennre/model/bag_average.py
opennre/model/bag_one.py
opennre/model/base_model.py
opennre/model/sigmoid_nn.py
opennre/model/softmax_nn.py
opennre/module/__init__.py
opennre/module/nn/__init__.py
opennre/module/nn/cnn.py
opennre/module/nn/lstm.py
opennre/module/nn/rnn.py
opennre/module/pool/__init__.py
opennre/module/pool/avg_pool.py
opennre/module/pool/max_pool.py
opennre/tokenization/__init__.py
opennre/tokenization/basic_tokenizer.py
opennre/tokenization/bert_tokenizer.py
opennre/tokenization/utils.py
opennre/tokenization/word_piece_tokenizer.py
opennre/tokenization/word_tokenizer.py